pybanana/__init__.py
pybanana/api.py
pybanana/enums.py
pybanana/models/__init__.py
pybanana/models/member.py
pybanana/models/result.py
pybanana/models/common/__init__.py
pybanana/models/common/bio.py
pybanana/models/common/buddy.py
pybanana/models/common/category.py
pybanana/models/common/credits.py
pybanana/models/common/discussion.py
pybanana/models/common/embeddable.py
pybanana/models/common/field.py
pybanana/models/common/file.py
pybanana/models/common/license.py
pybanana/models/common/managers.py
pybanana/models/common/medals.py
pybanana/models/common/moderators.py
pybanana/models/common/online.py
pybanana/models/common/preview.py
pybanana/models/common/profile.py
pybanana/models/common/ratings.py
pybanana/models/common/responses.py
pybanana/models/common/stats.py
pybanana/models/profiles/__init__.py
pybanana/models/profiles/app.py
pybanana/models/profiles/bug.py
pybanana/models/profiles/club.py
pybanana/models/profiles/game.py
pybanana/models/profiles/idea.py
pybanana/models/profiles/member.py
pybanana/models/profiles/mod.py
pybanana/models/profiles/studio.py
pybanana-0.5.0.dist-info/licenses/LICENSE
pybanana-0.5.0.dist-info/METADATA
pybanana-0.5.0.dist-info/WHEEL
pybanana-0.5.0.dist-info/top_level.txt
pybanana-0.5.0.dist-info/RECORD
